{
  "name": "Hero",
  "data": {
    "title": "Sample Title",
    "text": "Sample Text",
    "displaySearch": false,
    "image": {}
  },
  "form": {
    "schema": {
      "type": "object",

      "properties": {
        "title": {
          "type": "text",
          "title": "Title"
        },
        "text": {
          "type": "text",
          "title": "Text"
        },
        "displaySearch": {
          "type": "boolean",
          "title": "Display Search Bar?"
        },
        "image": {
          "type": "image"
        }
      }
    }
  }
}